fbxloader/__init__.py
fbxloader/converter.py
fbxloader/nodes.py
fbxloader/utils.py
fbxloader-0.0.2.dist-info/LICENSE
fbxloader-0.0.2.dist-info/METADATA
fbxloader-0.0.2.dist-info/WHEEL
fbxloader-0.0.2.dist-info/entry_points.txt
fbxloader-0.0.2.dist-info/top_level.txt
fbxloader-0.0.2.dist-info/RECORD
