Metadata-Version: 2.1
Name: fbxloader
Version: 0.0.2
Summary: utility to read fbx file
Home-page: https://github.com/ashawkey/fbxloader
Author: kiui
Author-email: ashawkey1999@gmail.com
Keywords: fbx
Classifier: Programming Language :: Python :: 3 
License-File: LICENSE
Requires-Dist: numpy
Requires-Dist: scipy
Requires-Dist: trimesh
